qcs_api_client_common-0.11.8.dist-info/METADATA
qcs_api_client_common-0.11.8.dist-info/WHEEL
qcs_api_client_common/grpc.py
qcs_api_client_common/configuration/__init__.pyi
qcs_api_client_common/configuration/__init__.py
qcs_api_client_common/__init__.pyi
qcs_api_client_common/httpx.py
qcs_api_client_common/__init__.py
qcs_api_client_common/py.typed
qcs_api_client_common/qcs_api_client_common.cpython-311-darwin.so
qcs_api_client_common-0.11.8.dist-info/RECORD
