Metadata-Version: 2.4
Name: qcs-api-client-common
Version: 0.11.8
Classifier: Development Status :: 3 - Alpha
Classifier: License :: OSI Approved :: Apache Software License
Classifier: Programming Language :: Python :: 3.9
Classifier: Programming Language :: Python :: 3.10
Classifier: Programming Language :: Python :: 3.11
Classifier: Programming Language :: Python :: 3.12
Classifier: Operating System :: OS Independent
Requires-Dist: grpcio >=1.63.0
Requires-Dist: grpc-interceptor >=0.15.0
Requires-Dist: httpx >=0.27.0
Requires-Dist: grpcio-testing >=1.63.0 ; extra == 'dev'
Requires-Dist: pytest >=8.1.1 ; extra == 'dev'
Requires-Dist: pytest-asyncio >=0.23.6 ; extra == 'dev'
Requires-Dist: pytest-mock >=3.14.0 ; extra == 'dev'
Requires-Dist: pytest-sugar >=1.0.0 ; extra == 'dev'
Requires-Dist: pytest-clarity >=1.0.1 ; extra == 'dev'
Requires-Dist: mypy >=1.4.1 ; extra == 'dev'
Requires-Dist: ruff >=0.3.5 ; extra == 'dev'
Requires-Dist: syrupy >=4.0.0 ; extra == 'dev'
Requires-Dist: watchdog[watchmedo] >=4.0.0 ; extra == 'dev'
Requires-Dist: maturin >=1.5.1 ; extra == 'dev'
Requires-Dist: sphinx >=7.3.7 ; extra == 'dev'
Requires-Dist: sphinx-autoapi >=3.0.0 ; extra == 'dev'
Requires-Dist: furo >=2024.5.6 ; extra == 'dev'
Provides-Extra: dev
Summary: Contains core QCS client functionality and middleware implementations.
Keywords: qcs,quantum,rigetti,api
Home-Page: https://github.com/rigetti/qcs-api-client-rust
Author-email: Rigetti Computing <softapps@rigetti.com>
License: Apache-2.0
Project-URL: Source Code, https://github.com/rigetti/qcs-api-client-rust
